rest_framework_api_key_allowbynames/__init__.py
rest_framework_api_key_allowbynames/decorator.py
djangorestframework_api_key_allowbynames-1.0.2.dist-info/LICENSE
djangorestframework_api_key_allowbynames-1.0.2.dist-info/METADATA
djangorestframework_api_key_allowbynames-1.0.2.dist-info/WHEEL
djangorestframework_api_key_allowbynames-1.0.2.dist-info/top_level.txt
djangorestframework_api_key_allowbynames-1.0.2.dist-info/RECORD
