Metadata-Version: 2.1
Name: djangorestframework-api-key-allowbynames
Version: 1.0.2
Summary: A djangorestframework-api-key decorator to allow access by key names
Home-page: https://github.com/mneitsabes/djangorestframework-api-key-allowbynames
Author: mneitsabes
Author-email: mneitsabes@nulloz.be
License: UNKNOWN
Keywords: django,djangorestframework-api-key
Platform: UNKNOWN
Classifier: Programming Language :: Python :: 3
Classifier: License :: OSI Approved :: MIT License
Classifier: Operating System :: OS Independent
Requires-Python: >=3.6
License-File: LICENSE
Requires-Dist: djangorestframework
Requires-Dist: djangorestframework-api-key
